xkeen_subscription_watcher/__init__.py
xkeen_subscription_watcher/main.py
xkeen_subscription_watcher/py.typed
xkeen_subscription_watcher-0.1.0.dist-info/licenses/LICENSE
xkeen_subscription_watcher-0.1.0.dist-info/METADATA
xkeen_subscription_watcher-0.1.0.dist-info/WHEEL
xkeen_subscription_watcher-0.1.0.dist-info/entry_points.txt
xkeen_subscription_watcher-0.1.0.dist-info/top_level.txt
xkeen_subscription_watcher-0.1.0.dist-info/RECORD
