Metadata-Version: 2.4
Name: xkeen-subscription-watcher
Version: 0.1.0
Summary: Add your description here
Author-email: Timofei Kukushkin <tima@kukushkin.me>
License-Expression: MIT
Project-URL: Homepage, https://github.com/tkukushkin/xkeen-subscription-watcher
Project-URL: Repository, https://github.com/tkukushkin/xkeen-subscription-watcher.git
Project-URL: Issues, https://github.com/tkukushkin/xkeen-subscription-watcher/issues
Project-URL: Changelog, https://github.com/tkukushkin/xkeen-subscription-watcher/releases
Requires-Python: >=3.11
License-File: LICENSE
Dynamic: license-file
